collective.feedaggregator-1.0a2-py2.7-nspkg.pth
collective/feedaggregator/__init__.py
collective/feedaggregator/config.py
collective/feedaggregator/configure.zcml
collective/feedaggregator/content.py
collective/feedaggregator/interfaces.py
collective/feedaggregator/logger.py
collective/feedaggregator/setuphandlers.py
collective/feedaggregator/testing.py
collective/feedaggregator/Extensions/Install.py
collective/feedaggregator/Extensions/__init__.py
collective/feedaggregator/browser/__init__.py
collective/feedaggregator/browser/configure.zcml
collective/feedaggregator/browser/feedaggregator.pt
collective/feedaggregator/browser/static/feedaggregator.png
collective/feedaggregator/browser/static/rss.svg
collective/feedaggregator/browser/static/tile-feedaggregator.png
collective/feedaggregator/profiles/default/browserlayer.xml
collective/feedaggregator/profiles/default/metadata.xml
collective/feedaggregator/profiles/default/registry.xml
collective/feedaggregator/profiles/default/rolemap.xml
collective/feedaggregator/profiles/default/types.xml
collective/feedaggregator/profiles/default/types/Feed_Aggregator.xml
collective/feedaggregator/tests/__init__.py
collective/feedaggregator/tests/test_content.py
collective/feedaggregator/tests/test_feedaggregator_tile.py
collective/feedaggregator/tests/test_setup.py
collective/feedaggregator/tiles/__init__.py
collective/feedaggregator/tiles/configure.zcml
collective/feedaggregator/tiles/feedaggregator.pt
collective/feedaggregator/tiles/feedaggregator.py
collective.feedaggregator-1.0a2.dist-info/DESCRIPTION.rst
collective.feedaggregator-1.0a2.dist-info/METADATA
collective.feedaggregator-1.0a2.dist-info/RECORD
collective.feedaggregator-1.0a2.dist-info/WHEEL
collective.feedaggregator-1.0a2.dist-info/entry_points.txt
collective.feedaggregator-1.0a2.dist-info/metadata.json
collective.feedaggregator-1.0a2.dist-info/namespace_packages.txt
collective.feedaggregator-1.0a2.dist-info/top_level.txt
