Metadata-Version: 2.0
Name: collective.feedaggregator
Version: 1.0a2
Summary: A feed aggregator content type for Plone.
Home-page: https://github.com/hvelarde/collective.feedaggregator
Author: Hector Velarde
Author-email: hector.velarde@gmail.com
License: UNKNOWN
Keywords: plone rss atom dexterity feed
Platform: UNKNOWN
Classifier: Development Status :: 3 - Alpha
Classifier: Environment :: Web Environment
Classifier: Framework :: Plone
Classifier: Framework :: Plone :: 4.3
Classifier: Framework :: Plone :: 5.0
Classifier: Framework :: Plone :: 5.1
Classifier: Intended Audience :: System Administrators
Classifier: License :: OSI Approved :: GNU General Public License v2 (GPLv2)
Classifier: Operating System :: OS Independent
Classifier: Programming Language :: Python
Classifier: Programming Language :: Python :: 2.7
Classifier: Topic :: Software Development :: Libraries :: Python Modules
Requires-Dist: Products.CMFPlone (>=4.3)
Requires-Dist: Products.GenericSetup
Requires-Dist: feedparser
Requires-Dist: plone.api
Requires-Dist: plone.app.content
Requires-Dist: plone.app.dexterity
Requires-Dist: plone.app.uuid
Requires-Dist: plone.dexterity
Requires-Dist: plone.memoize
Requires-Dist: plone.supermodel
Requires-Dist: profilehooks
Requires-Dist: setuptools
Requires-Dist: zope.globalrequest
Requires-Dist: zope.i18nmessageid
Requires-Dist: zope.interface
Requires-Dist: zope.schema
Provides-Extra: test
Requires-Dist: lxml; extra == 'test'
Requires-Dist: mock; extra == 'test'
Requires-Dist: plone.app.robotframework; extra == 'test'
Requires-Dist: plone.app.testing[robot]; extra == 'test'
Requires-Dist: plone.browserlayer; extra == 'test'
Requires-Dist: plone.testing; extra == 'test'
Requires-Dist: robotsuite; extra == 'test'
Requires-Dist: zope.component; extra == 'test'
